yai_nexus_agentkit/__init__.py
yai_nexus_agentkit/adapter/__init__.py
yai_nexus_agentkit/adapter/agui_adapter.py
yai_nexus_agentkit/adapter/errors.py
yai_nexus_agentkit/adapter/event_translator.py
yai_nexus_agentkit/adapter/langgraph_events.py
yai_nexus_agentkit/adapter/models.py
yai_nexus_agentkit/adapter/tool_call_tracker.py
yai_nexus_agentkit/core/__init__.py
yai_nexus_agentkit/core/checkpoint.py
yai_nexus_agentkit/core/embedding.py
yai_nexus_agentkit/core/events.py
yai_nexus_agentkit/core/logger_config.py
yai_nexus_agentkit/core/repository.py
yai_nexus_agentkit/core/utils.py
yai_nexus_agentkit/infrastructure/__init__.py
yai_nexus_agentkit/llm/__init__.py
yai_nexus_agentkit/llm/config.py
yai_nexus_agentkit/llm/factory.py
yai_nexus_agentkit/llm/models.py
yai_nexus_agentkit/llm/providers.py
yai_nexus_agentkit/llm/internal/registry.py
yai_nexus_agentkit/orchestration/__init__.py
yai_nexus_agentkit/persistence/__init__.py
yai_nexus_agentkit/persistence/checkpoint.py
yai_nexus_agentkit/persistence/db_config.py
yai_nexus_agentkit/persistence/repository.py
yai_nexus_agentkit/persistence/models/__init__.py
yai_nexus_agentkit/persistence/models/conversation.py
yai_nexus_agentkit/persistence/models/message.py
yai_nexus_agentkit-0.3.7.dist-info/METADATA
yai_nexus_agentkit-0.3.7.dist-info/WHEEL
yai_nexus_agentkit-0.3.7.dist-info/licenses/LICENSE
yai_nexus_agentkit-0.3.7.dist-info/RECORD
